{
    "records": [
        {
            "attributes": {
                "type": "Contact",
                "referenceId": "ContactRef1"
            },
            "Birthdate": "1979-03-23",
            "Email": "sofiarodriguez@example.com",
            "External_Id__c": "10008155",
            "FirstName": "Sofia",
            "Guest_Type__c": "Cultural Connoisseurs",
            "HasOptedOutOfEmail": false,
            "HasOptedOutOfFax": false,
            "Interest1__c": "Adventure Activities",
            "Interest2__c": "Beaches & Snorkeling",
            "Interest3__c": "Fitness & Exercise",
            "LastName": "Rodriguez",
            "LeadSource": "Direct Mail",
            "MailingCity": "Minneapolis",
            "MailingCountry": "United States",
            "MailingPostalCode": "55428",
            "MailingState": "Minnesota",
            "MailingStreet": "3 6th Avenue",
            "MobilePhone": "612-350-2240",
            "Next_Check_in_Date__c": "2024-08-23",
            "Photo_URL__c": "https://s3-us-west-2.amazonaws.com/dev-or-devrl-s3-bucket/sample-apps/coral-clouds/qswvurmhbo9w261cebby.png",
            "Preferred_Name__c": "Sofi",
            "AccountId": "@AccountRef1"
        },
        {
            "attributes": {
                "type": "Contact",
                "referenceId": "ContactRef2"
            },
            "Birthdate": "1972-10-24",
            "Department": "Procurement",
            "Email": "rose@edge.com",
            "Fax": "(512) 757-9000",
            "FirstName": "Rose",
            "HasOptedOutOfEmail": false,
            "HasOptedOutOfFax": false,
            "Languages__c": "English",
            "LastName": "Gonzalez",
            "LeadSource": "Trade Show",
            "Level__c": "Primary",
            "MailingStreet": "313 Constitution Place\nAustin, TX 78767\nUSA",
            "MobilePhone": "(512) 757-9340",
            "Phone": "(512) 757-6000",
            "Salutation": "Ms.",
            "Title": "SVP, Procurement",
            "AccountId": "@AccountRef2"
        },
        {
            "attributes": {
                "type": "Contact",
                "referenceId": "ContactRef3"
            },
            "Birthdate": "1951-07-23",
            "Department": "Finance",
            "Email": "sean@edge.com",
            "Fax": "(512) 757-9000",
            "FirstName": "Sean",
            "HasOptedOutOfEmail": false,
            "HasOptedOutOfFax": false,
            "Languages__c": "English",
            "LastName": "Forbes",
            "LeadSource": "Trade Show",
            "Level__c": "Secondary",
            "MailingStreet": "312 Constitution Place\nAustin, TX 78767\nUSA",
            "MobilePhone": "(512) 757-4561",
            "Phone": "(512) 757-6000",
            "Salutation": "Mr.",
            "Title": "CFO",
            "AccountId": "@AccountRef2"
        },
        {
            "attributes": {
                "type": "Contact",
                "referenceId": "ContactRef4"
            },
            "Email": "jrogers@burlington.com",
            "Fax": "(336) 222-8000",
            "FirstName": "Jack",
            "HasOptedOutOfEmail": false,
            "HasOptedOutOfFax": false,
            "LastName": "Rogers",
            "LeadSource": "Web",
            "MailingCity": "Burlington",
            "MailingCountry": "USA",
            "MailingPostalCode": "27215",
            "MailingState": "NC",
            "MailingStreet": "525 S. Lexington Ave",
            "Phone": "(336) 222-7000",
            "Salutation": "Mr.",
            "Title": "VP, Facilities",
            "AccountId": "@AccountRef3"
        },
        {
            "attributes": {
                "type": "Contact",
                "referenceId": "ContactRef5"
            },
            "AssistantName": "Jean Marie",
            "AssistantPhone": "(014) 427-4465",
            "Department": "Finance",
            "Email": "pat@pyramid.net",
            "Fax": "(014) 427-4428",
            "FirstName": "Pat",
            "HasOptedOutOfEmail": false,
            "HasOptedOutOfFax": false,
            "Languages__c": "French, English",
            "LastName": "Stumuller",
            "Level__c": "Primary",
            "MailingCity": "Paris",
            "MailingCountry": "France",
            "MailingPostalCode": "75251",
            "MailingStreet": "2 Place Jussieu",
            "MobilePhone": "(014) 454-6364",
            "OtherCity": "Paris",
            "OtherCountry": "France",
            "OtherPostalCode": "75251",
            "OtherStreet": "2 Place Jussieu",
            "Phone": "(014) 427-4427",
            "Salutation": "Ms.",
            "Title": "SVP, Administration and Finance",
            "AccountId": "@AccountRef4"
        },
        {
            "attributes": {
                "type": "Contact",
                "referenceId": "ContactRef6"
            },
            "Department": "Internal Operations",
            "Email": "a_young@dickenson.com",
            "FirstName": "Andy",
            "HasOptedOutOfEmail": false,
            "HasOptedOutOfFax": false,
            "Languages__c": "English",
            "LastName": "Young",
            "LeadSource": "Purchased List",
            "Level__c": "Primary",
            "MailingCity": "Lawrence",
            "MailingCountry": "USA",
            "MailingPostalCode": "66045",
            "MailingState": "KS",
            "MailingStreet": "1301 Hoch Drive",
            "MobilePhone": "(785) 265-5350",
            "OtherCity": "Lawrence",
            "OtherCountry": "USA",
            "OtherPostalCode": "66045",
            "OtherState": "KS",
            "OtherStreet": "1301 Hoch Drive",
            "Phone": "(785) 241-6200",
            "Salutation": "Mr",
            "Title": "SVP, Operations",
            "AccountId": "@AccountRef5"
        },
        {
            "attributes": {
                "type": "Contact",
                "referenceId": "ContactRef7"
            },
            "Birthdate": "1958-06-20",
            "Department": "Finance",
            "Email": "barr_tim@grandhotels.com",
            "Fax": "(312) 596-1500",
            "FirstName": "Tim",
            "HasOptedOutOfEmail": false,
            "HasOptedOutOfFax": false,
            "Languages__c": "English",
            "LastName": "Barr",
            "LeadSource": "External Referral",
            "Level__c": "Secondary",
            "MailingStreet": "2335 N. Michigan Avenue, Suite 1500\nChicago, IL 60601, USA",
            "MobilePhone": "(312) 596-1230",
            "Phone": "(312) 596-1000",
            "Salutation": "Mr.",
            "Title": "SVP, Administration and Finance",
            "AccountId": "@AccountRef6"
        },
        {
            "attributes": {
                "type": "Contact",
                "referenceId": "ContactRef8"
            },
            "Birthdate": "1960-08-31",
            "Department": "Facilities",
            "Email": "bond_john@grandhotels.com",
            "Fax": "(312) 596-1500",
            "FirstName": "John",
            "HasOptedOutOfEmail": false,
            "HasOptedOutOfFax": false,
            "Languages__c": "English",
            "LastName": "Bond",
            "LeadSource": "External Referral",
            "Level__c": "Primary",
            "MailingStreet": "2334 N. Michigan Avenue, Suite 1500\nChicago, IL 60601, USA",
            "MobilePhone": "(312) 596-1563",
            "Phone": "(312) 596-1000",
            "Salutation": "Mr.",
            "Title": "VP, Facilities",
            "AccountId": "@AccountRef6"
        },
        {
            "attributes": {
                "type": "Contact",
                "referenceId": "ContactRef9"
            },
            "AssistantName": "Audrey Haynes",
            "AssistantPhone": "(212) 842-5589",
            "Birthdate": "1948-02-15",
            "Department": "Production",
            "Email": "spavlova@uog.com",
            "Fax": "(212) 842-5501",
            "FirstName": "Stella",
            "HasOptedOutOfEmail": false,
            "HasOptedOutOfFax": false,
            "Languages__c": "English",
            "LastName": "Pavlova",
            "LeadSource": "Public Relations",
            "Level__c": "Tertiary",
            "MailingStreet": "1303 Avenue of the Americas \nNew York, NY 10019\nUSA",
            "MobilePhone": "(212) 842-5501",
            "OtherPhone": "(212) 842-5543",
            "Phone": "(212) 842-5500",
            "Salutation": "Ms.",
            "Title": "SVP, Production",
            "AccountId": "@AccountRef7"
        },
        {
            "attributes": {
                "type": "Contact",
                "referenceId": "ContactRef10"
            },
            "Birthdate": "1965-03-30",
            "Department": "Technology",
            "Email": "lboyle@uog.com",
            "Fax": "(212) 842-5501",
            "FirstName": "Lauren",
            "HasOptedOutOfEmail": false,
            "HasOptedOutOfFax": false,
            "Languages__c": "English",
            "LastName": "Boyle",
            "LeadSource": "Public Relations",
            "Level__c": "Secondary",
            "MailingStreet": "1304 Avenue of the Americas \nNew York, NY 10019\nUSA",
            "MobilePhone": "(212) 842-5611",
            "Phone": "(212) 842-5500",
            "Salutation": "Ms.",
            "Title": "SVP, Technology",
            "AccountId": "@AccountRef7"
        },
        {
            "attributes": {
                "type": "Contact",
                "referenceId": "ContactRef11"
            },
            "AssistantName": "Pat Feinstein",
            "AssistantPhone": "(212) 842-5464",
            "Birthdate": "1956-06-12",
            "Department": "Executive Team",
            "Email": "asong@uog.com",
            "Fax": "(212) 842-5501",
            "FirstName": "Arthur",
            "HasOptedOutOfEmail": false,
            "HasOptedOutOfFax": false,
            "Languages__c": "English",
            "LastName": "Song",
            "LeadSource": "Public Relations",
            "Level__c": "Secondary",
            "MailingStreet": "1301 Avenue of the Americas \nNew York, NY 10019\nUSA",
            "MobilePhone": "(212) 842-4535",
            "Phone": "(212) 842-5500",
            "Salutation": "Mr.",
            "Title": "CEO",
            "AccountId": "@AccountRef7"
        },
        {
            "attributes": {
                "type": "Contact",
                "referenceId": "ContactRef12"
            },
            "AssistantName": "Chris Nobel",
            "AssistantPhone": "(212) 842-5428",
            "Birthdate": "1938-05-24",
            "Department": "Finance",
            "Email": "agreen@uog.com",
            "Fax": "(212) 842-5501",
            "FirstName": "Avi",
            "HasOptedOutOfEmail": false,
            "HasOptedOutOfFax": false,
            "Languages__c": "English",
            "LastName": "Green",
            "LeadSource": "Public Relations",
            "Level__c": "Primary",
            "MailingStreet": "1302 Avenue of the Americas \nNew York, NY 10019\nUSA",
            "MobilePhone": "(212) 842-2383",
            "Phone": "(212) 842-5500",
            "Salutation": "Mr.",
            "Title": "CFO",
            "AccountId": "@AccountRef7"
        },
        {
            "attributes": {
                "type": "Contact",
                "referenceId": "ContactRef13"
            },
            "AssistantName": "Ron Sage",
            "AssistantPhone": "(503) 421-6782",
            "Birthdate": "1941-10-01",
            "Department": "Operations",
            "Email": "b.levy@expresslt.net",
            "Fax": "(503) 421-7801",
            "FirstName": "Babara",
            "HasOptedOutOfEmail": false,
            "HasOptedOutOfFax": false,
            "Languages__c": "English",
            "LastName": "Levy",
            "LeadSource": "Word of Mouth",
            "Level__c": "Primary",
            "MailingStreet": "620 SW 5th Avenue Suite 400\nPortland, Oregon 97204\nUnited States",
            "MobilePhone": "(503) 421-5451",
            "Phone": "(503) 421-7800",
            "Salutation": "Ms.",
            "Title": "SVP, Operations",
            "AccountId": "@AccountRef8"
        },
        {
            "attributes": {
                "type": "Contact",
                "referenceId": "ContactRef14"
            },
            "Birthdate": "1953-01-25",
            "Department": "Warehouse Mgmt",
            "Email": "j.davis@expresslt.net",
            "Fax": "(503) 421-7801",
            "FirstName": "Josh",
            "HasOptedOutOfEmail": false,
            "HasOptedOutOfFax": false,
            "Languages__c": "English",
            "LastName": "Davis",
            "LeadSource": "Word of Mouth",
            "Level__c": "Secondary",
            "MailingStreet": "621 SW 5th Avenue Suite 400\nPortland, Oregon 97204\nUnited States",
            "MobilePhone": "(503) 421-4387",
            "Phone": "(503) 421-7800",
            "Salutation": "Mr.",
            "Title": "Director, Warehouse Mgmt",
            "AccountId": "@AccountRef8"
        },
        {
            "attributes": {
                "type": "Contact",
                "referenceId": "ContactRef15"
            },
            "Birthdate": "1948-12-12",
            "Department": "Administration",
            "Email": "jane_gray@uoa.edu",
            "Fax": "(520) 773-9060",
            "FirstName": "Jane",
            "HasOptedOutOfEmail": false,
            "HasOptedOutOfFax": false,
            "Languages__c": "English",
            "LastName": "Grey",
            "LeadSource": "Word of Mouth",
            "Level__c": "Primary",
            "MailingStreet": "888 N Euclid \nHallis Center, Room 501\nTucson, AZ 85721\nUnited States",
            "MobilePhone": "(520) 773-4539",
            "Phone": "(520) 773-9050",
            "Salutation": "Ms.",
            "Title": "Dean of Administration",
            "AccountId": "@AccountRef9"
        },
        {
            "attributes": {
                "type": "Contact",
                "referenceId": "ContactRef16"
            },
            "Birthdate": "1951-02-20",
            "Department": "Finance",
            "Email": "ajames@uog.com",
            "Fax": "+44 191 4956620",
            "FirstName": "Ashley",
            "HasOptedOutOfEmail": false,
            "HasOptedOutOfFax": false,
            "Languages__c": "English",
            "LastName": "James",
            "LeadSource": "Public Relations",
            "Level__c": "Primary",
            "MailingStreet": "Kings Park, 17th Avenue, Team Valley Trading Estate,\nGateshead, Tyne and Wear NE26 3HS\nUnited Kingdom",
            "MobilePhone": "+44 191 3456234",
            "Phone": "+44 191 4956203",
            "Salutation": "Ms.",
            "Title": "VP, Finance",
            "AccountId": "@AccountRef10"
        },
        {
            "attributes": {
                "type": "Contact",
                "referenceId": "ContactRef17"
            },
            "Birthdate": "1955-04-19",
            "Department": "Executive Team",
            "Email": "tripley@uog.com",
            "Fax": "(650) 450-8820",
            "FirstName": "Tom",
            "HasOptedOutOfEmail": false,
            "HasOptedOutOfFax": false,
            "Languages__c": "English",
            "LastName": "Ripley",
            "LeadSource": "Public Relations",
            "Level__c": "Primary",
            "MailingStreet": "9 Tagore Lane\nSingapore, Singapore 787472\nSingapore",
            "MobilePhone": "(650) 345-7636",
            "Phone": "(650) 450-8810",
            "Salutation": "Mr.",
            "Title": "Regional General Manager",
            "AccountId": "@AccountRef11"
        },
        {
            "attributes": {
                "type": "Contact",
                "referenceId": "ContactRef18"
            },
            "Birthdate": "1966-07-30",
            "Department": "Production",
            "Email": "ldcruz@uog.com",
            "Fax": "(650) 450-8820",
            "FirstName": "Liz",
            "HasOptedOutOfEmail": false,
            "HasOptedOutOfFax": false,
            "Languages__c": "English",
            "LastName": "D'Cruz",
            "LeadSource": "Public Relations",
            "Level__c": "Secondary",
            "MailingStreet": "10 Tagore Lane\nSingapore, Singapore 787472\nSingapore",
            "MobilePhone": "(650) 345-6637",
            "Phone": "(650) 450-8810",
            "Salutation": "Ms.",
            "Title": "VP, Production",
            "AccountId": "@AccountRef11"
        },
        {
            "attributes": {
                "type": "Contact",
                "referenceId": "ContactRef19"
            },
            "Birthdate": "1947-01-04",
            "Department": "Technology",
            "Email": "efrank@genepoint.com",
            "Fax": "(650) 867-9895",
            "FirstName": "Edna",
            "HasOptedOutOfEmail": false,
            "HasOptedOutOfFax": false,
            "Languages__c": "English",
            "LastName": "Frank",
            "LeadSource": "Partner",
            "Level__c": "Primary",
            "MailingStreet": "345 Shoreline Park\nMountain View, CA 94043\nUSA",
            "MobilePhone": "(650) 867-7686",
            "Phone": "(650) 867-3450",
            "Salutation": "Ms.",
            "Title": "VP, Technology",
            "AccountId": "@AccountRef12"
        },
        {
            "attributes": {
                "type": "Contact",
                "referenceId": "ContactRef20"
            },
            "FirstName": "Siddartha",
            "HasOptedOutOfEmail": false,
            "HasOptedOutOfFax": false,
            "LastName": "Nedaerk",
            "MailingCity": "San Francisco",
            "MailingCountry": "US",
            "MailingPostalCode": "94087",
            "MailingState": "CA",
            "MailingStreet": "The Landmark @ One Market",
            "Salutation": "Ms.",
            "AccountId": "@AccountRef13"
        },
        {
            "attributes": {
                "type": "Contact",
                "referenceId": "ContactRef21"
            },
            "FirstName": "Jake",
            "HasOptedOutOfEmail": false,
            "HasOptedOutOfFax": false,
            "LastName": "Llorrac",
            "Salutation": "Mr.",
            "AccountId": "@AccountRef13"
        }
    ]
}